[
  {
    "id": "p_c38kgpy9",
    "address": "1048 Richland St, Maumee, Ohio 43537",
    "street": "1048 Richland St",
    "city": "Maumee",
    "state": "Ohio",
    "zip": "43537",
    "name": "WTR Kyle Camper",
    "priority": 3,
    "priorityLabel": "3",
    "priorityTime": "",
    "lastCheckin": "",
    "nextCheckin": "",
    "propertyType": "",
    "extra": {
      "Called Today": "FALSE",
      "Priority\n(1 = High)": "3",
      "Deal Name": "WTR Kyle Camper",
      "Project": "P132070",
      "Latest Status": "A. Scheduled",
      "Notes": "Cody meeting a family friend TUESDAY 10-11. Family is still in Aruba\n\nThe basement flooded during recent storm. They managed to dry it out but want a quote for water and mold mitigation",
      "Intake": "7/11/2026",
      "Days on List": "0",
      "Zestimate": "#N/A",
      "In HubSpot": "FALSE",
      "Email reply": "FALSE"
    },
    "lat": 41.5816444,
    "lng": -83.6253564,
    "status": "geocoded",
    "source": "sheet",
    "approx": false,
    "geoSource": "OpenStreetMap"
  },
  {
    "id": "p_6937yhty",
    "address": "21005 Carter Rd, Bowling Green, Ohio 43402",
    "street": "21005 Carter Rd",
    "city": "Bowling Green",
    "state": "Ohio",
    "zip": "43402",
    "name": "HAZ Alex Schultz",
    "priority": 3,
    "priorityLabel": "3",
    "priorityTime": "",
    "lastCheckin": "",
    "nextCheckin": "",
    "propertyType": "",
    "extra": {
      "Called Today": "FALSE",
      "Priority\n(1 = High)": "3",
      "Deal Name": "HAZ Alex Schultz",
      "Project": "P132306",
      "Latest Status": "B. Waitlist",
      "Notes": "419-308-7919 // Septic system collapsed and is being replaced. Sewage and water got into crawlspace. Will need to be pumped out and cleaned in coordination with C&L sanitation replacing the septic.",
      "Intake": "7/9/2026",
      "Days on List": "2",
      "Zestimate": "#N/A",
      "In HubSpot": "FALSE",
      "Email reply": "FALSE"
    },
    "lat": 40.5514939,
    "lng": -83.3577688,
    "status": "geocoded",
    "source": "sheet",
    "approx": true,
    "geoSource": "OpenStreetMap"
  },
  {
    "id": "p_ojjfc9z8",
    "address": "1036 Custer Dr, Toledo, Ohio 43612",
    "street": "1036 Custer Dr",
    "city": "Toledo",
    "state": "Ohio",
    "zip": "43612",
    "name": "MLD Anastasia Jagodzinski",
    "priority": 3,
    "priorityLabel": "3",
    "priorityTime": "",
    "lastCheckin": "",
    "nextCheckin": "",
    "propertyType": "",
    "extra": {
      "Called Today": "FALSE",
      "Priority\n(1 = High)": "3",
      "Deal Name": "MLD Anastasia Jagodzinski",
      "Project": "P132265",
      "Latest Status": "B. Waitlist",
      "Notes": "Mold remediation needed in the attic, this was notice a few months go when roof was replaced. Possibly a little mold in the bathroom, but not sure if it's actually mold. Would like an overall quote.\n\nI will call her Wednesday to check back in for availability on her end and ours.",
      "Intake": "7/8/2026",
      "Days on List": "2",
      "Zestimate": "#N/A",
      "In HubSpot": "FALSE",
      "Email reply": "FALSE"
    },
    "lat": 41.7081551,
    "lng": -83.5674558,
    "status": "geocoded",
    "source": "sheet",
    "approx": false,
    "geoSource": "OpenStreetMap"
  },
  {
    "id": "p_leojawhc",
    "address": "28683 E River Rd, Perrysburg, Ohio 43551",
    "street": "28683 E River Rd",
    "city": "Perrysburg",
    "state": "Ohio",
    "zip": "43551",
    "name": "WTR Nathan Egbet",
    "priority": 3,
    "priorityLabel": "3",
    "priorityTime": "",
    "lastCheckin": "",
    "nextCheckin": "",
    "propertyType": "",
    "extra": {
      "Called Today": "FALSE",
      "Priority\n(1 = High)": "3",
      "Deal Name": "WTR Nathan Egbet",
      "Project": "P132388",
      "Latest Status": "B. Waitlist",
      "Notes": "Sump pump went out flooding cst basement. \n\nThey’re in no immediate rush and offered Monday as an option. I told him I call him Monday morning and check in, but he can call if he needs anything in the meantime",
      "Intake": "7/10/2026",
      "Days on List": "0",
      "Zestimate": "#N/A",
      "In HubSpot": "FALSE",
      "Email reply": "FALSE"
    },
    "lat": 41.5682318,
    "lng": -83.6123308,
    "status": "geocoded",
    "source": "sheet",
    "approx": false,
    "geoSource": "OpenStreetMap"
  },
  {
    "id": "p_mj27pjzb",
    "address": "549 Park Way W, Oregon, Ohio 43616",
    "street": "549 Park Way W",
    "city": "Oregon",
    "state": "Ohio",
    "zip": "43616",
    "name": "WTR Sara Riegel",
    "priority": 3,
    "priorityLabel": "3",
    "priorityTime": "",
    "lastCheckin": "",
    "nextCheckin": "",
    "propertyType": "",
    "extra": {
      "Called Today": "FALSE",
      "Priority\n(1 = High)": "3",
      "Deal Name": "WTR Sara Riegel",
      "Project": "P132070",
      "Latest Status": "B. Waitlist",
      "Notes": "WAITLIST 7/6/26: Flooded basement - Sump pump could not keep up.",
      "Intake": "7/6/2026",
      "Days on List": "4",
      "Zestimate": "#N/A",
      "BD/Emp.": "Theresa Logan",
      "Questionnaire Complete": "Yes",
      "In HubSpot": "TRUE",
      "Email reply": "TRUE"
    },
    "lat": 41.6418947,
    "lng": -83.4266874,
    "status": "geocoded",
    "source": "sheet",
    "approx": false,
    "geoSource": "OpenStreetMap"
  },
  {
    "id": "p_wff7a5gj",
    "address": "25228 John F McCarthy Wy, Perrysburg, Perrysburg, Ohio 43551",
    "street": "25228 John F McCarthy Wy, Perrysburg",
    "city": "Perrysburg",
    "state": "Ohio",
    "zip": "43551",
    "name": "WTR Brent Patmos",
    "priority": 3,
    "priorityLabel": "3",
    "priorityTime": "",
    "lastCheckin": "",
    "nextCheckin": "",
    "propertyType": "",
    "extra": {
      "Called Today": "FALSE",
      "Priority\n(1 = High)": "3",
      "Deal Name": "WTR Brent Patmos",
      "Project": "P132345",
      "Latest Status": "C. VM x 1",
      "Notes": "WAITLIST JULY 2026 - Water damage from broken water heater and needs moisture check. Plumbers are coming to fix it, but humidity is high and needs water mitigation",
      "Intake": "7/9/2026",
      "Days on List": "1",
      "Zestimate": "#N/A",
      "In HubSpot": "FALSE",
      "Email reply": "FALSE"
    },
    "lat": 41.516335852905,
    "lng": -83.693459717934,
    "status": "geocoded",
    "source": "sheet",
    "approx": false,
    "geoSource": "US Census"
  },
  {
    "id": "p_lfpy5ls5",
    "address": "2715 N State Route 590, Graytown, Ohio 43432",
    "street": "2715 N State Route 590",
    "city": "Graytown",
    "state": "Ohio",
    "zip": "43432",
    "name": "WTR Charles Stansley",
    "priority": 1,
    "priorityLabel": "BD-1",
    "priorityTime": "",
    "lastCheckin": "",
    "nextCheckin": "",
    "propertyType": "",
    "extra": {
      "Called Today": "FALSE",
      "Priority\n(1 = High)": "BD-1",
      "Deal Name": "WTR Charles Stansley",
      "Project": "P132042",
      "Latest Status": "C. VM x 1",
      "Notes": "WAITLIST JULY 6,2026, 2 inches of water located in the finish basement.",
      "Intake": "7/6/2026",
      "Days on List": "4",
      "Inspection Scheduled": "7/9/2026",
      "Zestimate": "#N/A",
      "In HubSpot": "FALSE",
      "Email reply": "FALSE"
    },
    "lat": 41.555772046024,
    "lng": -83.22209950064,
    "status": "geocoded",
    "source": "sheet",
    "approx": false,
    "geoSource": "US Census"
  },
  {
    "id": "p_pssn4xre",
    "address": "1545 Cherry St, Millbury, Ohio 43447",
    "street": "1545 Cherry St",
    "city": "Millbury",
    "state": "Ohio",
    "zip": "43447",
    "name": "WTR Neil Riojas",
    "priority": 3,
    "priorityLabel": "3",
    "priorityTime": "",
    "lastCheckin": "",
    "nextCheckin": "",
    "propertyType": "",
    "extra": {
      "Called Today": "FALSE",
      "Priority\n(1 = High)": "3",
      "Deal Name": "WTR Neil Riojas",
      "Latest Status": "C. VM x 1",
      "Notes": "He has water in his basement",
      "Intake": "7/11/2026",
      "Days on List": "0",
      "Zestimate": "#N/A",
      "In HubSpot": "FALSE",
      "Email reply": "FALSE"
    },
    "lat": 41.5658213,
    "lng": -83.4255438,
    "status": "geocoded",
    "source": "sheet",
    "approx": false,
    "geoSource": "OpenStreetMap"
  },
  {
    "id": "p_kjzpyhl5",
    "address": "758 Maple St, Perrysburg, Ohio 43551",
    "street": "758 Maple St",
    "city": "Perrysburg",
    "state": "Ohio",
    "zip": "43551",
    "name": "WTR Roger Bowers",
    "priority": 3,
    "priorityLabel": "3",
    "priorityTime": "",
    "lastCheckin": "",
    "nextCheckin": "",
    "propertyType": "",
    "extra": {
      "Called Today": "FALSE",
      "Priority\n(1 = High)": "3",
      "Deal Name": "WTR Roger Bowers",
      "Project": "P132194",
      "Latest Status": "C. VM x 1",
      "Notes": "Has a toilet that is overflowing",
      "Intake": "7/7/2026",
      "Days on List": "3",
      "Zestimate": "#N/A",
      "In HubSpot": "FALSE",
      "Email reply": "FALSE"
    },
    "lat": 41.5551693,
    "lng": -83.6187367,
    "status": "geocoded",
    "source": "sheet",
    "approx": false,
    "geoSource": "OpenStreetMap"
  },
  {
    "id": "p_9t7w830g",
    "address": "1723 Perth St, Toledo, Ohio 43607",
    "street": "1723 Perth St",
    "city": "Toledo",
    "state": "Ohio",
    "zip": "43607",
    "name": "WTR Annie Smith",
    "priority": 3,
    "priorityLabel": "3",
    "priorityTime": "",
    "lastCheckin": "",
    "nextCheckin": "",
    "propertyType": "",
    "extra": {
      "Called Today": "FALSE",
      "Priority\n(1 = High)": "3",
      "Deal Name": "WTR Annie Smith",
      "Project": "P132255",
      "Latest Status": "D. VM x 2",
      "Notes": "WAITLIST JULY 8,2026 - Water damage located in the basement would like estimate.",
      "Intake": "7/8/2026",
      "Days on List": "2",
      "Zestimate": "#N/A",
      "In HubSpot": "FALSE",
      "Email reply": "FALSE"
    },
    "lat": 41.656423,
    "lng": -83.6013115,
    "status": "geocoded",
    "source": "sheet",
    "approx": false,
    "geoSource": "OpenStreetMap"
  },
  {
    "id": "p_85bcawwl",
    "address": "1709 N Curtice Rd, Curtice, Ohio 43412",
    "street": "1709 N Curtice Rd",
    "city": "Curtice",
    "state": "Ohio",
    "zip": "43412",
    "name": "WTR Paula McGrady",
    "priority": 3,
    "priorityLabel": "3",
    "priorityTime": "",
    "lastCheckin": "",
    "nextCheckin": "",
    "propertyType": "",
    "extra": {
      "Called Today": "FALSE",
      "Priority\n(1 = High)": "3",
      "Deal Name": "WTR Paula McGrady",
      "Project": "P132198",
      "Latest Status": "D. VM x 2",
      "Notes": "Basement had 5\" of water in it as sump pump couldn't keep up. They have drained water but need dry out and restoration.",
      "Intake": "7/8/2026",
      "Days on List": "3",
      "Zestimate": "#N/A",
      "In HubSpot": "FALSE",
      "Email reply": "FALSE"
    },
    "lat": 41.6204043,
    "lng": -83.3699217,
    "status": "geocoded",
    "source": "sheet",
    "approx": false,
    "geoSource": "OpenStreetMap"
  },
  {
    "id": "p_fyrx220z",
    "address": "1522 Bradner Rd, Northwood, Ohio 43619",
    "street": "1522 Bradner Rd",
    "city": "Northwood",
    "state": "Ohio",
    "zip": "43619",
    "name": "WTR Deb Hepner",
    "priority": 5,
    "priorityLabel": "5",
    "priorityTime": "",
    "lastCheckin": "",
    "nextCheckin": "",
    "propertyType": "",
    "extra": {
      "Called Today": "FALSE",
      "Priority\n(1 = High)": "Will Call Us",
      "Deal Name": "WTR Deb Hepner",
      "Project": "P131965",
      "Latest Status": "X. Will Call Us",
      "Notes": "Voicemail saying we know that she said she’d call us, but I wanted to check in before the weekend. Said to call me back if she has any needs.",
      "Intake": "7/6/2026",
      "Days on List": "5",
      "Zestimate": "$274,700.00",
      "In HubSpot": "FALSE",
      "Email reply": "FALSE"
    },
    "lat": 41.6086994,
    "lng": -83.4351477,
    "status": "geocoded",
    "source": "sheet",
    "approx": true,
    "geoSource": "OpenStreetMap"
  },
  {
    "id": "p_fsnkh20p",
    "address": "3207 Tersa Dr, Oregon, Ohio 43616",
    "street": "3207 Tersa Dr",
    "city": "Oregon",
    "state": "Ohio",
    "zip": "43616",
    "name": "WTR Elizabeth Steele",
    "priority": 5,
    "priorityLabel": "5",
    "priorityTime": "",
    "lastCheckin": "",
    "nextCheckin": "",
    "propertyType": "",
    "extra": {
      "Called Today": "FALSE",
      "Priority\n(1 = High)": "Will Call Us",
      "Deal Name": "WTR Elizabeth Steele",
      "Project": "P131945",
      "Latest Status": "X. Will Call Us",
      "Notes": "Doesn’t need anything right now. The damage was caused by the contractors and she doesn’t know if she can hire another contractor. She’s gonna check with her insurance company a call back or text back on my cell if she needs anything.",
      "Intake": "7/5/2026",
      "Days on List": "5",
      "Zestimate": "$357,000.00",
      "In HubSpot": "FALSE",
      "Email reply": "FALSE"
    },
    "lat": 41.631863908253,
    "lng": -83.47255930677,
    "status": "geocoded",
    "source": "sheet",
    "approx": false,
    "geoSource": "US Census"
  },
  {
    "id": "p_f8ab8z5m",
    "address": "24160 West Young Rd, Millbury, Ohio 43447",
    "street": "24160 West Young Rd",
    "city": "Millbury",
    "state": "Ohio",
    "zip": "43447",
    "name": "WTR Josie Schwalbe",
    "priority": 5,
    "priorityLabel": "5",
    "priorityTime": "",
    "lastCheckin": "",
    "nextCheckin": "",
    "propertyType": "",
    "extra": {
      "Called Today": "FALSE",
      "Priority\n(1 = High)": "Will Call Us",
      "Deal Name": "WTR Josie Schwalbe",
      "Project": "P131966",
      "Latest Status": "X. Will Call Us",
      "Notes": "Voicemail saying if she needs anything give me a call or text otherwise we’ll just keep her on her list and expect her to call when she needs something",
      "Intake": "7/6/2026",
      "Days on List": "5",
      "Zestimate": "$295,000.00",
      "In HubSpot": "FALSE",
      "Email reply": "FALSE"
    },
    "lat": 41.595782588767,
    "lng": -83.399327441512,
    "status": "geocoded",
    "source": "sheet",
    "approx": false,
    "geoSource": "US Census"
  }
]